rvnewop/BasicBlock.py
rvnewop/C32.py
rvnewop/Histogram.py
rvnewop/I32.py
rvnewop/M32.py
rvnewop/Program.py
rvnewop/RV32.py
rvnewop/RVFormatParser.py
rvnewop/RVInstruction.py
rvnewop/V32.py
rvnewop/__init__.py
rvnewop/__main__.py
rvnewop/main.py
rvnewop/unused.py
rvnewop-0.7.4.dist-info/entry_points.txt
rvnewop-0.7.4.dist-info/LICENSE
rvnewop-0.7.4.dist-info/WHEEL
rvnewop-0.7.4.dist-info/METADATA
rvnewop-0.7.4.dist-info/RECORD
