Metadata-Version: 2.1
Name: rvnewop
Version: 0.7.4
Summary: A RISC-V New Instruction Recommender System 
Home-page: https://github.com/riscv-newop/riscv-newop
License: BSD-2-Clause
Author: Pranoy Dutta, Tanvi Mehta, Nagendra Gulur
Author-email: pranoydll@gmail.com
Classifier: Intended Audience :: Developers
Classifier: License :: OSI Approved :: BSD License
Requires-Dist: bitarray >= 1.2.2
